Metadata-Version: 1.0
Name: jquerypluginbp
Version: 0.1.1
Summary: Script to generate boilerplate for your jQuery plugin
Home-page: UNKNOWN
Author: Andrea Stagi
Author-email: stagi.andrea@gmail.com
License: MIT
Keywords: jquery plugin script boilerplate
Platform: UNKNOWN
